VoicePy/ComponentsABC.py
VoicePy/DynamicClass.py
VoicePy/MyDict.py
VoicePy/NullComponent.py
VoicePy/VoicePlatformABC.py
VoicePy/__init__.py
VoicePy-0.1.dist-info/LICENSE
VoicePy-0.1.dist-info/METADATA
VoicePy-0.1.dist-info/WHEEL
VoicePy-0.1.dist-info/top_level.txt
VoicePy-0.1.dist-info/RECORD
