Metadata-Version: 2.1
Name: VoicePy
Version: 0.1
Summary: A Python Library to interface with Alexa, Dialogflow, and Google Actions
Home-page: https://github.com/mayankberi1/VoicePy
Author: Mayank Beri
Author-email: mayank@logicfactory.com.au
License: UNKNOWN
Platform: UNKNOWN
Classifier: Programming Language :: Python :: 3
Classifier: License :: OSI Approved :: GNU Lesser General Public License v3 or later (LGPLv3+)
Classifier: Operating System :: OS Independent
Requires-Python: >=3.6
